netlify_publish/__init__.py
netlify_publish/publish.py
netlify_publish-0.0.3.dist-info/LICENSE
netlify_publish-0.0.3.dist-info/METADATA
netlify_publish-0.0.3.dist-info/WHEEL
netlify_publish-0.0.3.dist-info/top_level.txt
netlify_publish-0.0.3.dist-info/RECORD
