Metadata-Version: 2.1
Name: netlify-publish
Version: 0.0.3
Summary: Publish to netlify
Home-page: https://github.com/commits-generation/netlify-publish
Author: Wassim Benzarti
Author-email: m.wassim.benzarti@gmail.com
License: UNKNOWN
Platform: UNKNOWN
Classifier: Programming Language :: Python :: 3
Classifier: License :: OSI Approved :: MIT License
Classifier: Operating System :: OS Independent
Requires-Python: >=3.6
